{
  "titlePositive": [
    "lecture",
    "tutorial",
    "class",
    "concept",
    "problem solving",
    "derivation",
    "pyq",
    "past year",
    "jee",
    "neet",
    "ncert",
    "revision",
    "mock test",
    "study with me",
    "physics",
    "chemistry",
    "biology",
    "mathematics",
    "calculus",
    "organic chemistry",
    "inorganic chemistry",
    "thermodynamics",
    "open course",
    "algorithm",
    "data structures",
    "machine learning",
    "notes",
    "exam strategy",
    "time management"
  ],
  "descriptionPositive": [
    "syllabus",
    "exam",
    "chapter",
    "concept explanation",
    "detailed solution",
    "practice questions",
    "live class",
    "free course",
    "education",
    "students",
    "iit-jee",
    "jee mains",
    "jee advanced",
    "neet ug",
    "cbse",
    "assignment",
    "homework",
    "learning outcomes"
  ],
  "negativeTitle": [
    "prank",
    "vlog",
    "roast",
    "reaction",
    "meme",
    "edit",
    "challenge",
    "shorts",
    "funny",
    "troll",
    "asmr",
    "unboxing",
    "gameplay",
    "stream highlights",
    "celebrity",
    "gossip",
    "clip dump"
  ],
  "entertainmentChannels": [
    "mrbeast",
    "sidemen",
    "carryminati",
    "ishowspeed",
    "kai cenat",
    "pewdiepie",
    "faze",
    "dr disrespect",
    "linus tech tips shorts",
    "viralhog",
    "netflix",
    "prime video",
    "t-series"
  ],
  "playlistWhitelist": [
    "PLUl4u3cNGP63WbdFxL8giv4yhgdMGaZNA",
    "PLRJdqdXieSHN0U9AdnmwD-9QcR9hmw04d",
    "PLVLoWQFkZbhWZf7j5lBZWfVo3vL9M4r6I",
    "PL9ooVrP1hQOG4Y4T4fK2a4GqvCF2v4Wf7"
  ]
}
